ui_forge/__init__.py
ui_forge/actions.py
ui_forge/items.py
ui_forge/selector.py
ui_forge/ui.py
ui_forge-2.2.1.dist-info/LICENSE
ui_forge-2.2.1.dist-info/METADATA
ui_forge-2.2.1.dist-info/WHEEL
ui_forge-2.2.1.dist-info/top_level.txt
ui_forge-2.2.1.dist-info/RECORD
