Metadata-Version: 2.1
Name: ui_forge
Version: 2.2.1
Summary: A WIP procedurally generated TUI made in NCurses using Python for CCSM
Author-email: CJ <cjendantix@proton.me>
License: Unlicense
Keywords: curses,ui
Classifier: Development Status :: 4 - Beta
Classifier: Environment :: Console :: Curses
Classifier: License :: OSI Approved :: The Unlicense (Unlicense)
Classifier: Typing :: Typed
Classifier: Programming Language :: Python :: 3
Classifier: Operating System :: OS Independent
Requires-Python: >=3.12
License-File: LICENSE
Requires-Dist: windows-curses ; platform_system == "Windows"
